txdocumint/__init__.py
txdocumint/__init__.pyc
txdocumint/_client.py
txdocumint/_client.pyc
txdocumint/_version.py
txdocumint/_version.pyc
txdocumint/actions.py
txdocumint/actions.pyc
txdocumint/error.py
txdocumint/error.pyc
txdocumint/test/__init__.py
txdocumint/test/__init__.pyc
txdocumint/test/test_actions.py
txdocumint/test/test_actions.pyc
txdocumint/test/test_client.py
txdocumint/test/test_client.pyc
txdocumint-18.0.1.dist-info/DESCRIPTION.rst
txdocumint-18.0.1.dist-info/METADATA
txdocumint-18.0.1.dist-info/RECORD
txdocumint-18.0.1.dist-info/WHEEL
txdocumint-18.0.1.dist-info/metadata.json
txdocumint-18.0.1.dist-info/top_level.txt
